aphin/__init__.py
aphin/identification/__init__.py
aphin/identification/aphin.py
aphin/identification/conv_aphin.py
aphin/identification/ph_basemodel.py
aphin/identification/phin.py
aphin/identification/projection_aphin.py
aphin/layers/__init__.py
aphin/layers/descriptor_ph_layer.py
aphin/layers/lti_layer.py
aphin/layers/ph_layer.py
aphin/layers/phq_layer.py
aphin/layers/system_layer.py
aphin/operators/__init__.py
aphin/operators/linear_operator_skew_sym.py
aphin/operators/linear_operator_sym.py
aphin/operators/linear_operator_sym_pos_def.py
aphin/operators/operator_utils.py
aphin/systems/__init__.py
aphin/systems/lti_systems.py
aphin/systems/ph_systems.py
aphin/utils/__init__.py
aphin/utils/callbacks_tensorflow.py
aphin/utils/configuration.py
aphin/utils/experiments.py
aphin/utils/integrators.py
aphin/utils/print_matrices.py
aphin/utils/save_results.py
aphin/utils/transformations.py
aphin/utils/visualizations.py
aphin/utils/data/__init__.py
aphin/utils/data/data.py
aphin/utils/data/dataset.py
aphin-1.1.dist-info/licenses/LICENSE
aphin-1.1.dist-info/METADATA
aphin-1.1.dist-info/WHEEL
aphin-1.1.dist-info/top_level.txt
aphin-1.1.dist-info/RECORD
