Metadata-Version: 2.4
Name: aphin
Version: 1.1
Summary: Autoencoder-based port-Hamiltonian Identification Networks (ApHIN) is a Python package for structure-preserving model order reduction and system identification of port-Hamiltonian systems.
Author-email: Jonas Kneifl <jonas.kneifl@itm.uni-stuttgart.com>, Johannes Rettberg <johannes.rettberg@itm.uni-stuttgart.com>, Julius Herb <julius.herb@mib.uni-stuttgart.com>
Project-URL: Homepage, https://github.com/Institute-Eng-and-Comp-Mechanics-UStgt/ApHIN
Project-URL: Issues, https://github.com/Institute-Eng-and-Comp-Mechanics-UStgt/ApHIN/issues
Keywords: structure-preserving model order reduction,system identification,surrogate modeling,reduced order models,port-Hamiltonian systems
Classifier: Programming Language :: Python :: 3
Classifier: License :: OSI Approved :: MIT License
Classifier: Operating System :: OS Independent
Requires-Python: >=3.11
License-File: LICENSE
Requires-Dist: matplotlib==3.9
Requires-Dist: numpy>=1.21.4
Requires-Dist: scikit_learn>=1.2
Requires-Dist: scikit_optimize>=0.10
Requires-Dist: scipy>=1.10
Requires-Dist: tensorflow>=2.15
Requires-Dist: tensorflow_probability>=0.24
Requires-Dist: tensorflow_model_optimization>=0.7
Requires-Dist: tf-keras>=2.16
Requires-Dist: PyYAML>=6
Requires-Dist: pandas>=1.3.4
Requires-Dist: natsort>=8.4.0
Requires-Dist: tqdm>=4.66.2
Requires-Dist: pymor>=2023.2.0
Requires-Dist: visualizer-3d>=0.3
Provides-Extra: gui
Provides-Extra: interfaces
Dynamic: license-file
